ALU_ROL_5bit.v
module ALU_ROL_5bit
(
    input [4:0] in,
    input [2:0] shift,
    output reg [4:0] out
);

always @(*) begin
    case(shift)
        3'b000: out = in;
        3'b001: out = {in[3:0], in[4]};
        3'b010: out = {in[2:0], in[4:3]};
        3'b011: out = {in[1:0], in[4:2]};
        3'b100: out = {in[0], in[4:1]};
        default: out = in;
    endcase
end

endmodule

ALU_NOT_5bit.v
module ALU_NOT_5bit
(
    input wire [4:0] A,  
    output wire [4:0] result
);

assign result = ~A;

endmodule

ALU.v
module ALU
(
    input wire [4:0] A, B,                   
    input wire OP,    
    output reg [4:0] result,     
    output wire CF,
    output wire SF,
    output wire ZF           
);

    wire [4:0] R_NOT, R_ROL;

    // Instantiate modules
    ALU_NOT_5bit NOT1 ( .A(A), .result(R_NOT));
    ALU_ROL_5bit ROL1 ( .in(A), .shift(B[2:0]), .out(R_ROL));  // last 3 bits of input B

    always @(*) 
    begin
        case (OP)
            1'b0: // NOT 
                begin 
                    result = R_NOT; 
                end
            1'b1: // ROL
                begin 
                    result = R_ROL;
                end
            
            default: 
                begin
                    result = 5'b00000;  
                end
        endcase
    end

    assign CF = 1'b0;
    assign SF = result[4];
    assign ZF = ~(result[4] | result[3] | result[2] | result[1] | result[0]);

endmodule

controller.v
module controller(
    input wire clk,
    input wire reset,
    output reg [4:0] A,
    output reg [4:0] B,
    output reg OP,
    output reg [4:0] result,
    output reg flag,
    output reg done
);

    // Define states
    parameter [2:0] START = 3'b000,
                    ONE   = 3'b001,
                    TWO   = 3'b010,
                    THREE = 3'b011,
                    FINISH = 3'b100;

    reg [2:0] pstate, nstate;

    // State Register
    always @(posedge clk or posedge reset) begin
        if (reset)
            pstate <= START;
        else
            pstate <= nstate;
    end

    // Next State and Outputs
    always @(*) begin
        // Default outputs
        A = 5'b00000;
        B = 5'b00000;
        OP = 1'b0;
        flag = 1'b0;
        done = 1'b0;
        nstate = pstate;

        case (pstate)
            START: begin
                nstate = ONE;
            end
            
            ONE: begin
                A = 5'b00101;   // Test NOT operation
                B = 5'b00000;
                OP = 1'b0;
                nstate = TWO;
            end

            TWO: begin
                A = 5'b10000;   // Test ROL operation (shift 1)
                B = 5'b00001;
                OP = 1'b1;
                nstate = THREE;
            end

            THREE: begin
                A = 5'b00000;   // Test NOT operation with all zeros (flag should be 0)
                B = 5'b00000;
                OP = 1'b0;
                nstate = FINISH;
            end

            FINISH: begin
                done = 1'b1;
                nstate = FINISH;  // Stay in FINISH state until reset
            end

            default: nstate = START;
        endcase
    end

endmodule

top.v
module top(
    input wire clk,
    input wire reset,
    output wire [4:0] result,
    output wire flag_gt_zero,
    output wire done
);

    // Internal wires
    wire [4:0] A, B;
    wire OP;
    wire [4:0] R_result;
    wire SF, ZF;

    // Instantiate controller
    controller controller1 (
        .clk(clk),
        .reset(reset),
        .A(A),
        .B(B),
        .OP(OP),
        .result(result),
        .flag(flag_gt_zero),
        .done(done)
    );

    // Instantiate ALU datapath
    ALU datapath1 (
        .A(A),
        .B(B),
        .OP(OP),
        .result(R_result),
        .CF(),          // Carry flag (unused)
        .SF(SF),        // Sign flag
        .ZF(ZF)         // Zero flag
    );

    // Output assignments
    assign result = R_result;
    assign flag_gt_zero = SF;  // Flag is 1 when result > 0 (using sign flag)

endmodule

top_tb.v
`timescale 1ns/1ns

module top_tb;

    // Inputs
    reg clk, reset;
    
    // Outputs
    wire [4:0] result;
    wire flag_gt_zero;
    wire done;

    // Instantiate Unit Under Test
    top uut (
        .clk(clk),
        .reset(reset),
        .result(result),
        .flag_gt_zero(flag_gt_zero),
        .done(done)
    );

    // Clock generator (100MHz)
    initial begin
        clk = 0;
        forever #5 clk = ~clk;
    end

    // Test sequence
    initial begin
        // Initialize waveform dump
        $dumpfile("top_test.vcd");
        $dumpvars(0, top_tb);
        
        // Reset sequence
        reset = 1;
        #10;
        reset = 0;
        
        // Wait for completion or timeout
        wait(done == 1 || $time >= 200);
        
        // Additional delay for observation
        #20;
        
        $display("Test completed at time = %0t ns", $time);
        $finish;
    end

    // Monitor to display signals
    initial begin
        $monitor("Time = %0t ns | State = %b | A = %b | B = %b | OP = %b | Result = %b | Flag = %b | Done = %b",
                 $time,
                 uut.controller1.pstate,
                 uut.controller1.A,
                 uut.controller1.B,
                 uut.controller1.OP,
                 result,
                 flag_gt_zero,
                 done);
    end

endmodule

ALU_tb.v
`timescale 1ns/1ps
module ALU_tb;

    reg [4:0] A, B;       
    reg OP;          
    wire [4:0] R;          
    wire CF;
    wire SF;
    wire ZF;

    ALU uut (
        .A(A),
        .B(B),
        .OP(OP),
        .result(R),
        .CF(CF),
        .SF(SF),
        .ZF(ZF)
    );

    initial begin
        $dumpfile("alu_test.vcd");
        $dumpvars(0, ALU_tb);

        // Test NOT operation
        A = 5'b00101; B = 5'b00000; OP = 1'b0;
        #10;
        
        // Test ROL operation with shift 1
        A = 5'b10000; B = 5'b00001; OP = 1'b1;
        #10;
        
        // Test ROL operation with shift 3
        A = 5'b10110; B = 5'b00011; OP = 1'b1;
        #10;
        
        // Test edge case with all zeros
        A = 5'b00000; B = 5'b00000; OP = 1'b0;
        #10;
        
        // Test edge case with all ones
        A = 5'b11111; B = 5'b00000; OP = 1'b0;
        #10;

        $finish;
    end

    initial begin
        $monitor("Time=%0t A=%b B=%b OP=%b -> R=%b CF=%b ZF=%b SF=%b", $time, A, B, OP, R, CF, ZF, SF);
    end

endmodule

alu_test.vcd
$date
	Fri Jun 13 20:59:27 2025
$end
$version
	Icarus Verilog
$end
$timescale
	1ps
$end
$scope module ALU_tb $end
$var wire 1 ! CF $end
$var wire 1 " ZF $end
$var wire 1 # SF $end
$var wire 5 $ R [4:0] $end
$var reg 5 % A [4:0] $end
$var reg 5 & B [4:0] $end
$var reg 1 ' OP $end
$scope module uut $end
$var wire 5 ( A [4:0] $end
$var wire 5 ) B [4:0] $end
$var wire 1 ! CF $end
$var wire 1 ' OP $end
$var wire 1 " ZF $end
$var wire 1 # SF $end
$var wire 5 * R_ROL [4:0] $end
$var wire 5 + R_NOT [4:0] $end
$var reg 5 , result [4:0] $end
$scope module NOT1 $end
$var wire 5 - A [4:0] $end
$var wire 5 . result [4:0] $end
$upscope $end
$scope module ROL1 $end
$var wire 5 / in [4:0] $end
$var wire 3 0 shift [2:0] $end
$var reg 5 1 out [4:0] $end
$upscope $end
$upscope $end
$upscope $end
$scope module top_tb $end
$var wire 1 2 flag_gt_zero $end
$var wire 5 3 result [4:0] $end
$var wire 1 4 done $end
$var reg 1 5 clk $end
$var reg 1 6 reset $end
$scope module uut $end
$var wire 1 5 clk $end
$var wire 1 2 flag_gt_zero $end
$var wire 1 6 reset $end
$var wire 5 7 result [4:0] $end
$var wire 1 4 done $end
$var wire 1 8 ZF $end
$var wire 1 9 SF $end
$var wire 5 : R_result [4:0] $end
$var wire 1 ; OP $end
$var wire 5 < B [4:0] $end
$var wire 5 = A [4:0] $end
$scope module controller1 $end
$var wire 1 5 clk $end
$var wire 1 6 reset $end
$var parameter 3 > FINISH $end
$var parameter 3 ? ONE $end
$var parameter 3 @ START $end
$var parameter 3 A THREE $end
$var parameter 3 B TWO $end
$var reg 5 C A [4:0] $end
$var reg 5 D B [4:0] $end
$var reg 1 ; OP $end
$var reg 1 4 done $end
$var reg 1 E flag $end
$var reg 3 F nstate [2:0] $end
$var reg 3 G pstate [2:0] $end
$var reg 5 H result [4:0] $end
$upscope $end
$scope module datapath1 $end
$var wire 5 I A [4:0] $end
$var wire 5 J B [4:0] $end
$var wire 1 K CF $end
$var wire 1 ; OP $end
$var wire 1 8 ZF $end
$var wire 1 9 SF $end
$var wire 5 L R_ROL [4:0] $end
$var wire 5 M R_NOT [4:0] $end
$var reg 5 N result [4:0] $end
$scope module NOT1 $end
$var wire 5 O A [4:0] $end
$var wire 5 P result [4:0] $end
$upscope $end
$scope module ROL1 $end
$var wire 5 Q in [4:0] $end
$var wire 3 R shift [2:0] $end
$var reg 5 S out [4:0] $end
$upscope $end
$upscope $end
$upscope $end
$upscope $end
$enddefinitions $end
$comment Show the parameter values. $end
$dumpall
b10 B
b11 A
b0 @
b1 ?
b100 >
$end
#0
$dumpvars
b0 S
b0 R
b0 Q
b11111 P
b0 O
b11111 N
b11111 M
b0 L
0K
b0 J
b0 I
bx H
b0 G
b1 F
0E
b0 D
b0 C
b0 =
b0 <
0;
b11111 :
19
08
bx 7
16
05
04
bx 3
x2
b101 1
b0 0
b101 /
b11010 .
b101 -
b11010 ,
b11010 +
b101 *
b0 )
b101 (
0'
b0 &
b101 %
b11010 $
1#
0"
0!
$end
#5000
15
#10000
0#
b1 $
b1 ,
b1 0
b1111 +
b1111 .
b1 *
b1 1
05
06
1'
b1 &
b1 )
b10000 %
b10000 (
b10000 -
b10000 /
#15000
b11010 :
b11010 N
b11010 M
b11010 P
b101 L
b101 S
b10 F
b101 =
b101 C
b101 I
b101 O
b101 Q
b1 G
15
#20000
1#
b10101 $
b10101 ,
b11 0
b1001 +
b1001 .
b10101 *
b10101 1
05
b11 &
b11 )
b10110 %
b10110 (
b10110 -
b10110 /
#25000
02
09
b1 :
b1 N
b1 R
b1111 M
b1111 P
b1 L
b1 S
b11 F
1;
b1 <
b1 D
b1 J
b10000 =
b10000 C
b10000 I
b10000 O
b10000 Q
b10 G
15
#30000
b11111 $
b11111 ,
b0 0
b11111 +
b11111 .
b0 *
b0 1
05
0'
b0 &
b0 )
b0 %
b0 (
b0 -
b0 /
#35000
x2
19
b11111 :
b11111 N
b0 R
b11111 M
b11111 P
b0 L
b0 S
b100 F
0;
b0 <
b0 D
b0 J
b0 =
b0 C
b0 I
b0 O
b0 Q
b11 G
15
#40000
1"
0#
b0 $
b0 ,
b0 +
b0 .
b11111 *
b11111 1
05
b11111 %
b11111 (
b11111 -
b11111 /
#45000
14
b100 G
15
